vsim_uart/uart.v
module uart
#(
    parameter DELAY_FRAMES = 234 // 27,000,000 (27Mhz) / 115200 Baud rate
)
(
    input clk,
    input uart_rx,
    output uart_tx,
    output reg [5:0] led,
    input btn1
);

localparam HALF_DELAY_WAIT = (DELAY_FRAMES / 2);

reg [3:0] rxState = 0;
reg [12:0] rxCounter = 0;
reg [7:0] dataIn = 0;
reg [2:0] rxBitNumber = 0;
reg byteReady = 0;

localparam RX_STATE_IDLE = 0;
localparam RX_STATE_START_BIT = 1;
localparam RX_STATE_READ_WAIT = 2;
localparam RX_STATE_READ = 3;
localparam RX_STATE_STOP_BIT = 5;

always @(posedge clk) begin
    case (rxState)
        RX_STATE_IDLE: begin
            if (uart_rx == 0) begin
                rxState <= RX_STATE_START_BIT;
                rxCounter <= 1;
                rxBitNumber <= 0;
                byteReady <= 0;
            end
        end 
        RX_STATE_START_BIT: begin
            if (rxCounter == HALF_DELAY_WAIT) begin
                rxState <= RX_STATE_READ_WAIT;
                rxCounter <= 1;
            end else 
                rxCounter <= rxCounter + 1;
        end
        RX_STATE_READ_WAIT: begin
            rxCounter <= rxCounter + 1;
            if ((rxCounter + 1) == DELAY_FRAMES) begin
                rxState <= RX_STATE_READ;
            end
        end
        RX_STATE_READ: begin
            rxCounter <= 1;
            dataIn <= {uart_rx, dataIn[7:1]};
            rxBitNumber <= rxBitNumber + 1;
            if (rxBitNumber == 3'b111)
                rxState <= RX_STATE_STOP_BIT;
            else
                rxState <= RX_STATE_READ_WAIT;
        end
        RX_STATE_STOP_BIT: begin
            rxCounter <= rxCounter + 1;
            if ((rxCounter + 1) == DELAY_FRAMES) begin
                rxState <= RX_STATE_IDLE;
                rxCounter <= 0;
                byteReady <= 1;
            end
        end
    endcase
end

always @(posedge clk) begin
    if (byteReady) begin
        led <= ~dataIn[5:0];
    end
end

reg [3:0] txState = 0;
reg [24:0] txCounter = 0;
reg [7:0] dataOut = 0;
reg txPinRegister = 1;
reg [2:0] txBitNumber = 0;
reg [3:0] txByteCounter = 0;

assign uart_tx = txPinRegister;

localparam MEMORY_LENGTH = 12;
reg [7:0] testMemory [MEMORY_LENGTH-1:0];

initial begin
    testMemory[0] = "L";
    testMemory[1] = "u";
    testMemory[2] = "s";
    testMemory[3] = "h";
    testMemory[4] = "a";
    testMemory[5] = "y";
    testMemory[6] = " ";
    testMemory[7] = "L";
    testMemory[8] = "a";
    testMemory[9] = "b";
    testMemory[10] = "s";
    testMemory[11] = " ";
end

localparam TX_STATE_IDLE = 0;
localparam TX_STATE_START_BIT = 1;
localparam TX_STATE_WRITE = 2;
localparam TX_STATE_STOP_BIT = 3;
localparam TX_STATE_DEBOUNCE = 4;

always @(posedge clk) begin
    case (txState)
        TX_STATE_IDLE: begin
            if (btn1 == 0) begin
                txState <= TX_STATE_START_BIT;
                txCounter <= 0;
                txByteCounter <= 0;
            end
            else begin
                txPinRegister <= 1;
            end
        end 
        TX_STATE_START_BIT: begin
            txPinRegister <= 0;
            if ((txCounter + 1) == DELAY_FRAMES) begin
                txState <= TX_STATE_WRITE;
                dataOut <= testMemory[txByteCounter];
                txBitNumber <= 0;
                txCounter <= 0;
            end else 
                txCounter <= txCounter + 1;
        end
        TX_STATE_WRITE: begin
            txPinRegister <= dataOut[txBitNumber];
            if ((txCounter + 1) == DELAY_FRAMES) begin
                if (txBitNumber == 3'b111) begin
                    txState <= TX_STATE_STOP_BIT;
                end else begin
                    txState <= TX_STATE_WRITE;
                    txBitNumber <= txBitNumber + 1;
                end
                txCounter <= 0;
            end else 
                txCounter <= txCounter + 1;
        end
        TX_STATE_STOP_BIT: begin
            txPinRegister <= 1;
            if ((txCounter + 1) == DELAY_FRAMES) begin
                if (txByteCounter == MEMORY_LENGTH - 1) begin
                    txState <= TX_STATE_DEBOUNCE;
                end else begin
                    txByteCounter <= txByteCounter + 1;
                    txState <= TX_STATE_START_BIT;
                end
                txCounter <= 0;
            end else 
                txCounter <= txCounter + 1;
        end
        TX_STATE_DEBOUNCE: begin
            if (txCounter == 23'b111111111111111111) begin
                if (btn1 == 1) 
                    txState <= TX_STATE_IDLE;
            end else
                txCounter <= txCounter + 1;
        end
    endcase      
end
endmodule

vsim_uart/uart_tb.v

module test();
  reg clk = 0;
  reg uart_rx = 1;
  wire uart_tx;
  wire [5:0] led;
  reg btn = 1;

  uart #(8'd8) u(
    clk,
    uart_rx,
    uart_tx,
    led,
    btn
  );

  always
    #1  clk = ~clk;

  initial begin
    $display("Starting UART RX");
    $monitor("LED Value %b", led);
    #10 uart_rx=0;
    #16 uart_rx=1;
    #16 uart_rx=0;
    #16 uart_rx=0;
    #16 uart_rx=0;
    #16 uart_rx=0;
    #16 uart_rx=1;
    #16 uart_rx=1;
    #16 uart_rx=0;
    #16 uart_rx=1;
    #4 btn=0;
    #4 btn=1;
    #1000 $stop;
  end

  initial begin
    $dumpfile("uart.vcd");
    $dumpvars(0,test);
  end
endmodule

vsim_uart/uart.vcd
$date
	Thu May  9 16:43:50 2024
$end
$version
	ModelSim Version 2020.1
$end
$timescale
	1ps
$end

$scope module test $end
$var reg 1 ! clk $end
$var reg 1 " uart_rx $end
$var wire 1 # uart_tx $end
$var wire 1 $ led [5] $end
$var wire 1 % led [4] $end
$var wire 1 & led [3] $end
$var wire 1 ' led [2] $end
$var wire 1 ( led [1] $end
$var wire 1 ) led [0] $end
$var reg 1 * btn $end

$scope module u $end
$var parameter 8 + DELAY_FRAMES $end
$var parameter 32 , HALF_DELAY_WAIT $end
$var parameter 32 - RX_STATE_IDLE $end
$var parameter 32 . RX_STATE_START_BIT $end
$var parameter 32 / RX_STATE_READ_WAIT $end
$var parameter 32 0 RX_STATE_READ $end
$var parameter 32 1 RX_STATE_STOP_BIT $end
$var parameter 32 2 MEMORY_LENGTH $end
$var parameter 32 3 TX_STATE_IDLE $end
$var parameter 32 4 TX_STATE_START_BIT $end
$var parameter 32 5 TX_STATE_WRITE $end
$var parameter 32 6 TX_STATE_STOP_BIT $end
$var parameter 32 7 TX_STATE_DEBOUNCE $end
$var wire 1 8 clk $end
$var wire 1 9 uart_rx $end
$var wire 1 # uart_tx $end
$var reg 6 : led [5:0] $end
$var wire 1 ; btn1 $end
$var reg 4 < rxState [3:0] $end
$var reg 13 = rxCounter [12:0] $end
$var reg 8 > dataIn [7:0] $end
$var reg 3 ? rxBitNumber [2:0] $end
$var reg 1 @ byteReady $end
$var reg 4 A txState [3:0] $end
$var reg 25 B txCounter [24:0] $end
$var reg 8 C dataOut [7:0] $end
$var reg 1 D txPinRegister $end
$var reg 3 E txBitNumber [2:0] $end
$var reg 4 F txByteCounter [3:0] $end
$upscope $end
$upscope $end
$enddefinitions $end
#0
$dumpvars
0!
1"
1*
bx :
b0 <
b0 =
b0 >
b0 ?
0@
b0 A
b0 B
b0 C
1D
b0 E
b0 F
b1000 +
b100 ,
b0 -
b1 .
b10 /
b11 0
b101 1
b1100 2
b0 3
b1 4
b10 5
b11 6
b100 7
1#
x)
x(
x'
x&
x%
x$
1;
19
08
$end
#1
1!
18
#2
0!
08
#3
1!
18
#4
0!
08
#5
1!
18
#6
0!
08
#7
1!
18
#8
0!
08
#9
1!
18
#10
0"
0!
09
08
#11
1!
18
b1 <
b1 =
#12
0!
08
#13
1!
18
b10 =
#14
0!
08
#15
1!
18
b11 =
#16
0!
08
#17
1!
18
b100 =
#18
0!
08
#19
1!
18
b10 <
b1 =
#20
0!
08
#21
1!
18
b10 =
#22
0!
08
#23
1!
18
b11 =
#24
0!
08
#25
1!
18
b100 =
#26
1"
0!
19
08
#27
1!
18
b101 =
#28
0!
08
#29
1!
18
b110 =
#30
0!
08
#31
1!
18
b111 =
#32
0!
08
#33
1!
18
b1000 =
b11 <
#34
0!
08
#35
1!
18
b1 =
b10000000 >
b1 ?
b10 <
#36
0!
08
#37
1!
18
b10 =
#38
0!
08
#39
1!
18
b11 =
#40
0!
08
#41
1!
18
b100 =
#42
0"
0!
09
08
#43
1!
18
b101 =
#44
0!
08
#45
1!
18
b110 =
#46
0!
08
#47
1!
18
b111 =
#48
0!
08
#49
1!
18
b1000 =
b11 <
#50
0!
08
#51
1!
18
b1 =
b1000000 >
b10 ?
b10 <
#52
0!
08
#53
1!
18
b10 =
#54
0!
08
#55
1!
18
b11 =
#56
0!
08
#57
1!
18
b100 =
#58
0!
08
#59
1!
18
b101 =
#60
0!
08
#61
1!
18
b110 =
#62
0!
08
#63
1!
18
b111 =
#64
0!
08
#65
1!
18
b1000 =
b11 <
#66
0!
08
#67
1!
18
b1 =
b100000 >
b11 ?
b10 <
#68
0!
08
#69
1!
18
b10 =
#70
0!
08
#71
1!
18
b11 =
#72
0!
08
#73
1!
18
b100 =
#74
0!
08
#75
1!
18
b101 =
#76
0!
08
#77
1!
18
b110 =
#78
0!
08
#79
1!
18
b111 =
#80
0!
08
#81
1!
18
b1000 =
b11 <
#82
0!
08
#83
1!
18
b1 =
b10000 >
b100 ?
b10 <
#84
0!
08
#85
1!
18
b10 =
#86
0!
08
#87
1!
18
b11 =
#88
0!
08
#89
1!
18
b100 =
#90
0!
08
#91
1!
18
b101 =
#92
0!
08
#93
1!
18
b110 =
#94
0!
08
#95
1!
18
b111 =
#96
0!
08
#97
1!
18
b1000 =
b11 <
#98
0!
08
#99
1!
18
b1 =
b1000 >
b101 ?
b10 <
#100
0!
08
#101
1!
18
b10 =
#102
0!
08
#103
1!
18
b11 =
#104
0!
08
#105
1!
18
b100 =
#106
1"
0!
19
08
#107
1!
18
b101 =
#108
0!
08
#109
1!
18
b110 =
#110
0!
08
#111
1!
18
b111 =
#112
0!
08
#113
1!
18
b1000 =
b11 <
#114
0!
08
#115
1!
18
b1 =
b10000100 >
b110 ?
b10 <
#116
0!
08
#117
1!
18
b10 =
#118
0!
08
#119
1!
18
b11 =
#120
0!
08
#121
1!
18
b100 =
#122
0!
08
#123
1!
18
b101 =
#124
0!
08
#125
1!
18
b110 =
#126
0!
08
#127
1!
18
b111 =
#128
0!
08
#129
1!
18
b1000 =
b11 <
#130
0!
08
#131
1!
18
b1 =
b11000010 >
b111 ?
b10 <
#132
0!
08
#133
1!
18
b10 =
#134
0!
08
#135
1!
18
b11 =
#136
0!
08
#137
1!
18
b100 =
#138
0"
0!
09
08
#139
1!
18
b101 =
#140
0!
08
#141
1!
18
b110 =
#142
0!
08
#143
1!
18
b111 =
#144
0!
08
#145
1!
18
b1000 =
b11 <
#146
0!
08
#147
1!
18
b1 =
b1100001 >
b0 ?
b101 <
#148
0!
08
#149
1!
18
b10 =
#150
0!
08
#151
1!
18
b11 =
#152
0!
08
#153
1!
18
b100 =
#154
1"
0!
19
08
#155
1!
18
b101 =
#156
0!
08
#157
1!
18
b110 =
#158
0*
0!
0;
08
#159
1!
18
b111 =
b1 A
#160
0!
08
#161
1!
18
b1000 =
b0 <
b0 =
1@
0D
b1 B
0#
#162
1*
0!
1;
08
#163
1!
18
b11110 :
b10 B
0)
1(
1'
1&
1%
0$
#164
0!
08
#165
1!
18
b11 B
#166
0!
08
#167
1!
18
b100 B
#168
0!
08
#169
1!
18
b101 B
#170
0!
08
#171
1!
18
b110 B
#172
0!
08
#173
1!
18
b111 B
#174
0!
08
#175
1!
18
b10 A
b1001100 C
b0 B
#176
0!
08
#177
1!
18
b1 B
#178
0!
08
#179
1!
18
b10 B
#180
0!
08
#181
1!
18
b11 B
#182
0!
08
#183
1!
18
b100 B
#184
0!
08
#185
1!
18
b101 B
#186
0!
08
#187
1!
18
b110 B
#188
0!
08
#189
1!
18
b111 B
#190
0!
08
#191
1!
18
b1 E
b0 B
#192
0!
08
#193
1!
18
b1 B
#194
0!
08
#195
1!
18
b10 B
#196
0!
08
#197
1!
18
b11 B
#198
0!
08
#199
1!
18
b100 B
#200
0!
08
#201
1!
18
b101 B
#202
0!
08
#203
1!
18
b110 B
#204
0!
08
#205
1!
18
b111 B
#206
0!
08
#207
1!
18
b10 E
b0 B
#208
0!
08
#209
1!
18
1D
b1 B
1#
#210
0!
08
#211
1!
18
b10 B
#212
0!
08
#213
1!
18
b11 B
#214
0!
08
#215
1!
18
b100 B
#216
0!
08
#217
1!
18
b101 B
#218
0!
08
#219
1!
18
b110 B
#220
0!
08
#221
1!
18
b111 B
#222
0!
08
#223
1!
18
b11 E
b0 B
#224
0!
08
#225
1!
18
b1 B
#226
0!
08
#227
1!
18
b10 B
#228
0!
08
#229
1!
18
b11 B
#230
0!
08
#231
1!
18
b100 B
#232
0!
08
#233
1!
18
b101 B
#234
0!
08
#235
1!
18
b110 B
#236
0!
08
#237
1!
18
b111 B
#238
0!
08
#239
1!
18
b100 E
b0 B
#240
0!
08
#241
1!
18
0D
b1 B
0#
#242
0!
08
#243
1!
18
b10 B
#244
0!
08
#245
1!
18
b11 B
#246
0!
08
#247
1!
18
b100 B
#248
0!
08
#249
1!
18
b101 B
#250
0!
08
#251
1!
18
b110 B
#252
0!
08
#253
1!
18
b111 B
#254
0!
08
#255
1!
18
b101 E
b0 B
#256
0!
08
#257
1!
18
b1 B
#258
0!
08
#259
1!
18
b10 B
#260
0!
08
#261
1!
18
b11 B
#262
0!
08
#263
1!
18
b100 B
#264
0!
08
#265
1!
18
b101 B
#266
0!
08
#267
1!
18
b110 B
#268
0!
08
#269
1!
18
b111 B
#270
0!
08
#271
1!
18
b110 E
b0 B
#272
0!
08
#273
1!
18
1D
b1 B
1#
#274
0!
08
#275
1!
18
b10 B
#276
0!
08
#277
1!
18
b11 B
#278
0!
08
#279
1!
18
b100 B
#280
0!
08
#281
1!
18
b101 B
#282
0!
08
#283
1!
18
b110 B
#284
0!
08
#285
1!
18
b111 B
#286
0!
08
#287
1!
18
b111 E
b0 B
#288
0!
08
#289
1!
18
0D
b1 B
0#
#290
0!
08
#291
1!
18
b10 B
#292
0!
08
#293
1!
18
b11 B
#294
0!
08
#295
1!
18
b100 B
#296
0!
08
#297
1!
18
b101 B
#298
0!
08
#299
1!
18
b110 B
#300
0!
08
#301
1!
18
b111 B
#302
0!
08
#303
1!
18
b11 A
b0 B
#304
0!
08
#305
1!
18
1D
b1 B
1#
#306
0!
08
#307
1!
18
b10 B
#308
0!
08
#309
1!
18
b11 B
#310
0!
08
#311
1!
18
b100 B
#312
0!
08
#313
1!
18
b101 B
#314
0!
08
#315
1!
18
b110 B
#316
0!
08
#317
1!
18
b111 B
#318
0!
08
#319
1!
18
b1 F
b1 A
b0 B
#320
0!
08
#321
1!
18
0D
b1 B
0#
#322
0!
08
#323
1!
18
b10 B
#324
0!
08
#325
1!
18
b11 B
#326
0!
08
#327
1!
18
b100 B
#328
0!
08
#329
1!
18
b101 B
#330
0!
08
#331
1!
18
b110 B
#332
0!
08
#333
1!
18
b111 B
#334
0!
08
#335
1!
18
b10 A
b1110101 C
b0 E
b0 B
#336
0!
08
#337
1!
18
1D
b1 B
1#
#338
0!
08
#339
1!
18
b10 B
#340
0!
08
#341
1!
18
b11 B
#342
0!
08
#343
1!
18
b100 B
#344
0!
08
#345
1!
18
b101 B
#346
0!
08
#347
1!
18
b110 B
#348
0!
08
#349
1!
18
b111 B
#350
0!
08
#351
1!
18
b1 E
b0 B
#352
0!
08
#353
1!
18
0D
b1 B
0#
#354
0!
08
#355
1!
18
b10 B
#356
0!
08
#357
1!
18
b11 B
#358
0!
08
#359
1!
18
b100 B
#360
0!
08
#361
1!
18
b101 B
#362
0!
08
#363
1!
18
b110 B
#364
0!
08
#365
1!
18
b111 B
#366
0!
08
#367
1!
18
b10 E
b0 B
#368
0!
08
#369
1!
18
1D
b1 B
1#
#370
0!
08
#371
1!
18
b10 B
#372
0!
08
#373
1!
18
b11 B
#374
0!
08
#375
1!
18
b100 B
#376
0!
08
#377
1!
18
b101 B
#378
0!
08
#379
1!
18
b110 B
#380
0!
08
#381
1!
18
b111 B
#382
0!
08
#383
1!
18
b11 E
b0 B
#384
0!
08
#385
1!
18
0D
b1 B
0#
#386
0!
08
#387
1!
18
b10 B
#388
0!
08
#389
1!
18
b11 B
#390
0!
08
#391
1!
18
b100 B
#392
0!
08
#393
1!
18
b101 B
#394
0!
08
#395
1!
18
b110 B
#396
0!
08
#397
1!
18
b111 B
#398
0!
08
#399
1!
18
b100 E
b0 B
#400
0!
08
#401
1!
18
1D
b1 B
1#
#402
0!
08
#403
1!
18
b10 B
#404
0!
08
#405
1!
18
b11 B
#406
0!
08
#407
1!
18
b100 B
#408
0!
08
#409
1!
18
b101 B
#410
0!
08
#411
1!
18
b110 B
#412
0!
08
#413
1!
18
b111 B
#414
0!
08
#415
1!
18
b101 E
b0 B
#416
0!
08
#417
1!
18
b1 B
#418
0!
08
#419
1!
18
b10 B
#420
0!
08
#421
1!
18
b11 B
#422
0!
08
#423
1!
18
b100 B
#424
0!
08
#425
1!
18
b101 B
#426
0!
08
#427
1!
18
b110 B
#428
0!
08
#429
1!
18
b111 B
#430
0!
08
#431
1!
18
b110 E
b0 B
#432
0!
08
#433
1!
18
b1 B
#434
0!
08
#435
1!
18
b10 B
#436
0!
08
#437
1!
18
b11 B
#438
0!
08
#439
1!
18
b100 B
#440
0!
08
#441
1!
18
b101 B
#442
0!
08
#443
1!
18
b110 B
#444
0!
08
#445
1!
18
b111 B
#446
0!
08
#447
1!
18
b111 E
b0 B
#448
0!
08
#449
1!
18
0D
b1 B
0#
#450
0!
08
#451
1!
18
b10 B
#452
0!
08
#453
1!
18
b11 B
#454
0!
08
#455
1!
18
b100 B
#456
0!
08
#457
1!
18
b101 B
#458
0!
08
#459
1!
18
b110 B
#460
0!
08
#461
1!
18
b111 B
#462
0!
08
#463
1!
18
b11 A
b0 B
#464
0!
08
#465
1!
18
1D
b1 B
1#
#466
0!
08
#467
1!
18
b10 B
#468
0!
08
#469
1!
18
b11 B
#470
0!
08
#471
1!
18
b100 B
#472
0!
08
#473
1!
18
b101 B
#474
0!
08
#475
1!
18
b110 B
#476
0!
08
#477
1!
18
b111 B
#478
0!
08
#479
1!
18
b10 F
b1 A
b0 B
#480
0!
08
#481
1!
18
0D
b1 B
0#
#482
0!
08
#483
1!
18
b10 B
#484
0!
08
#485
1!
18
b11 B
#486
0!
08
#487
1!
18
b100 B
#488
0!
08
#489
1!
18
b101 B
#490
0!
08
#491
1!
18
b110 B
#492
0!
08
#493
1!
18
b111 B
#494
0!
08
#495
1!
18
b10 A
b1110011 C
b0 E
b0 B
#496
0!
08
#497
1!
18
1D
b1 B
1#
#498
0!
08
#499
1!
18
b10 B
#500
0!
08
#501
1!
18
b11 B
#502
0!
08
#503
1!
18
b100 B
#504
0!
08
#505
1!
18
b101 B
#506
0!
08
#507
1!
18
b110 B
#508
0!
08
#509
1!
18
b111 B
#510
0!
08
#511
1!
18
b1 E
b0 B
#512
0!
08
#513
1!
18
b1 B
#514
0!
08
#515
1!
18
b10 B
#516
0!
08
#517
1!
18
b11 B
#518
0!
08
#519
1!
18
b100 B
#520
0!
08
#521
1!
18
b101 B
#522
0!
08
#523
1!
18
b110 B
#524
0!
08
#525
1!
18
b111 B
#526
0!
08
#527
1!
18
b10 E
b0 B
#528
0!
08
#529
1!
18
0D
b1 B
0#
#530
0!
08
#531
1!
18
b10 B
#532
0!
08
#533
1!
18
b11 B
#534
0!
08
#535
1!
18
b100 B
#536
0!
08
#537
1!
18
b101 B
#538
0!
08
#539
1!
18
b110 B
#540
0!
08
#541
1!
18
b111 B
#542
0!
08
#543
1!
18
b11 E
b0 B
#544
0!
08
#545
1!
18
b1 B
#546
0!
08
#547
1!
18
b10 B
#548
0!
08
#549
1!
18
b11 B
#550
0!
08
#551
1!
18
b100 B
#552
0!
08
#553
1!
18
b101 B
#554
0!
08
#555
1!
18
b110 B
#556
0!
08
#557
1!
18
b111 B
#558
0!
08
#559
1!
18
b100 E
b0 B
#560
0!
08
#561
1!
18
1D
b1 B
1#
#562
0!
08
#563
1!
18
b10 B
#564
0!
08
#565
1!
18
b11 B
#566
0!
08
#567
1!
18
b100 B
#568
0!
08
#569
1!
18
b101 B
#570
0!
08
#571
1!
18
b110 B
#572
0!
08
#573
1!
18
b111 B
#574
0!
08
#575
1!
18
b101 E
b0 B
#576
0!
08
#577
1!
18
b1 B
#578
0!
08
#579
1!
18
b10 B
#580
0!
08
#581
1!
18
b11 B
#582
0!
08
#583
1!
18
b100 B
#584
0!
08
#585
1!
18
b101 B
#586
0!
08
#587
1!
18
b110 B
#588
0!
08
#589
1!
18
b111 B
#590
0!
08
#591
1!
18
b110 E
b0 B
#592
0!
08
#593
1!
18
b1 B
#594
0!
08
#595
1!
18
b10 B
#596
0!
08
#597
1!
18
b11 B
#598
0!
08
#599
1!
18
b100 B
#600
0!
08
#601
1!
18
b101 B
#602
0!
08
#603
1!
18
b110 B
#604
0!
08
#605
1!
18
b111 B
#606
0!
08
#607
1!
18
b111 E
b0 B
#608
0!
08
#609
1!
18
0D
b1 B
0#
#610
0!
08
#611
1!
18
b10 B
#612
0!
08
#613
1!
18
b11 B
#614
0!
08
#615
1!
18
b100 B
#616
0!
08
#617
1!
18
b101 B
#618
0!
08
#619
1!
18
b110 B
#620
0!
08
#621
1!
18
b111 B
#622
0!
08
#623
1!
18
b11 A
b0 B
#624
0!
08
#625
1!
18
1D
b1 B
1#
#626
0!
08
#627
1!
18
b10 B
#628
0!
08
#629
1!
18
b11 B
#630
0!
08
#631
1!
18
b100 B
#632
0!
08
#633
1!
18
b101 B
#634
0!
08
#635
1!
18
b110 B
#636
0!
08
#637
1!
18
b111 B
#638
0!
08
#639
1!
18
b11 F
b1 A
b0 B
#640
0!
08
#641
1!
18
0D
b1 B
0#
#642
0!
08
#643
1!
18
b10 B
#644
0!
08
#645
1!
18
b11 B
#646
0!
08
#647
1!
18
b100 B
#648
0!
08
#649
1!
18
b101 B
#650
0!
08
#651
1!
18
b110 B
#652
0!
08
#653
1!
18
b111 B
#654
0!
08
#655
1!
18
b10 A
b1101000 C
b0 E
b0 B
#656
0!
08
#657
1!
18
b1 B
#658
0!
08
#659
1!
18
b10 B
#660
0!
08
#661
1!
18
b11 B
#662
0!
08
#663
1!
18
b100 B
#664
0!
08
#665
1!
18
b101 B
#666
0!
08
#667
1!
18
b110 B
#668
0!
08
#669
1!
18
b111 B
#670
0!
08
#671
1!
18
b1 E
b0 B
#672
0!
08
#673
1!
18
b1 B
#674
0!
08
#675
1!
18
b10 B
#676
0!
08
#677
1!
18
b11 B
#678
0!
08
#679
1!
18
b100 B
#680
0!
08
#681
1!
18
b101 B
#682
0!
08
#683
1!
18
b110 B
#684
0!
08
#685
1!
18
b111 B
#686
0!
08
#687
1!
18
b10 E
b0 B
#688
0!
08
#689
1!
18
b1 B
#690
0!
08
#691
1!
18
b10 B
#692
0!
08
#693
1!
18
b11 B
#694
0!
08
#695
1!
18
b100 B
#696
0!
08
#697
1!
18
b101 B
#698
0!
08
#699
1!
18
b110 B
#700
0!
08
#701
1!
18
b111 B
#702
0!
08
#703
1!
18
b11 E
b0 B
#704
0!
08
#705
1!
18
1D
b1 B
1#
#706
0!
08
#707
1!
18
b10 B
#708
0!
08
#709
1!
18
b11 B
#710
0!
08
#711
1!
18
b100 B
#712
0!
08
#713
1!
18
b101 B
#714
0!
08
#715
1!
18
b110 B
#716
0!
08
#717
1!
18
b111 B
#718
0!
08
#719
1!
18
b100 E
b0 B
#720
0!
08
#721
1!
18
0D
b1 B
0#
#722
0!
08
#723
1!
18
b10 B
#724
0!
08
#725
1!
18
b11 B
#726
0!
08
#727
1!
18
b100 B
#728
0!
08
#729
1!
18
b101 B
#730
0!
08
#731
1!
18
b110 B
#732
0!
08
#733
1!
18
b111 B
#734
0!
08
#735
1!
18
b101 E
b0 B
#736
0!
08
#737
1!
18
1D
b1 B
1#
#738
0!
08
#739
1!
18
b10 B
#740
0!
08
#741
1!
18
b11 B
#742
0!
08
#743
1!
18
b100 B
#744
0!
08
#745
1!
18
b101 B
#746
0!
08
#747
1!
18
b110 B
#748
0!
08
#749
1!
18
b111 B
#750
0!
08
#751
1!
18
b110 E
b0 B
#752
0!
08
#753
1!
18
b1 B
#754
0!
08
#755
1!
18
b10 B
#756
0!
08
#757
1!
18
b11 B
#758
0!
08
#759
1!
18
b100 B
#760
0!
08
#761
1!
18
b101 B
#762
0!
08
#763
1!
18
b110 B
#764
0!
08
#765
1!
18
b111 B
#766
0!
08
#767
1!
18
b111 E
b0 B
#768
0!
08
#769
1!
18
0D
b1 B
0#
#770
0!
08
#771
1!
18
b10 B
#772
0!
08
#773
1!
18
b11 B
#774
0!
08
#775
1!
18
b100 B
#776
0!
08
#777
1!
18
b101 B
#778
0!
08
#779
1!
18
b110 B
#780
0!
08
#781
1!
18
b111 B
#782
0!
08
#783
1!
18
b11 A
b0 B
#784
0!
08
#785
1!
18
1D
b1 B
1#
#786
0!
08
#787
1!
18
b10 B
#788
0!
08
#789
1!
18
b11 B
#790
0!
08
#791
1!
18
b100 B
#792
0!
08
#793
1!
18
b101 B
#794
0!
08
#795
1!
18
b110 B
#796
0!
08
#797
1!
18
b111 B
#798
0!
08
#799
1!
18
b100 F
b1 A
b0 B
#800
0!
08
#801
1!
18
0D
b1 B
0#
#802
0!
08
#803
1!
18
b10 B
#804
0!
08
#805
1!
18
b11 B
#806
0!
08
#807
1!
18
b100 B
#808
0!
08
#809
1!
18
b101 B
#810
0!
08
#811
1!
18
b110 B
#812
0!
08
#813
1!
18
b111 B
#814
0!
08
#815
1!
18
b10 A
b1100001 C
b0 E
b0 B
#816
0!
08
#817
1!
18
1D
b1 B
1#
#818
0!
08
#819
1!
18
b10 B
#820
0!
08
#821
1!
18
b11 B
#822
0!
08
#823
1!
18
b100 B
#824
0!
08
#825
1!
18
b101 B
#826
0!
08
#827
1!
18
b110 B
#828
0!
08
#829
1!
18
b111 B
#830
0!
08
#831
1!
18
b1 E
b0 B
#832
0!
08
#833
1!
18
0D
b1 B
0#
#834
0!
08
#835
1!
18
b10 B
#836
0!
08
#837
1!
18
b11 B
#838
0!
08
#839
1!
18
b100 B
#840
0!
08
#841
1!
18
b101 B
#842
0!
08
#843
1!
18
b110 B
#844
0!
08
#845
1!
18
b111 B
#846
0!
08
#847
1!
18
b10 E
b0 B
#848
0!
08
#849
1!
18
b1 B
#850
0!
08
#851
1!
18
b10 B
#852
0!
08
#853
1!
18
b11 B
#854
0!
08
#855
1!
18
b100 B
#856
0!
08
#857
1!
18
b101 B
#858
0!
08
#859
1!
18
b110 B
#860
0!
08
#861
1!
18
b111 B
#862
0!
08
#863
1!
18
b11 E
b0 B
#864
0!
08
#865
1!
18
b1 B
#866
0!
08
#867
1!
18
b10 B
#868
0!
08
#869
1!
18
b11 B
#870
0!
08
#871
1!
18
b100 B
#872
0!
08
#873
1!
18
b101 B
#874
0!
08
#875
1!
18
b110 B
#876
0!
08
#877
1!
18
b111 B
#878
0!
08
#879
1!
18
b100 E
b0 B
#880
0!
08
#881
1!
18
b1 B
#882
0!
08
#883
1!
18
b10 B
#884
0!
08
#885
1!
18
b11 B
#886
0!
08
#887
1!
18
b100 B
#888
0!
08
#889
1!
18
b101 B
#890
0!
08
#891
1!
18
b110 B
#892
0!
08
#893
1!
18
b111 B
#894
0!
08
#895
1!
18
b101 E
b0 B
#896
0!
08
#897
1!
18
1D
b1 B
1#
#898
0!
08
#899
1!
18
b10 B
#900
0!
08
#901
1!
18
b11 B
#902
0!
08
#903
1!
18
b100 B
#904
0!
08
#905
1!
18
b101 B
#906
0!
08
#907
1!
18
b110 B
#908
0!
08
#909
1!
18
b111 B
#910
0!
08
#911
1!
18
b110 E
b0 B
#912
0!
08
#913
1!
18
b1 B
#914
0!
08
#915
1!
18
b10 B
#916
0!
08
#917
1!
18
b11 B
#918
0!
08
#919
1!
18
b100 B
#920
0!
08
#921
1!
18
b101 B
#922
0!
08
#923
1!
18
b110 B
#924
0!
08
#925
1!
18
b111 B
#926
0!
08
#927
1!
18
b111 E
b0 B
#928
0!
08
#929
1!
18
0D
b1 B
0#
#930
0!
08
#931
1!
18
b10 B
#932
0!
08
#933
1!
18
b11 B
#934
0!
08
#935
1!
18
b100 B
#936
0!
08
#937
1!
18
b101 B
#938
0!
08
#939
1!
18
b110 B
#940
0!
08
#941
1!
18
b111 B
#942
0!
08
#943
1!
18
b11 A
b0 B
#944
0!
08
#945
1!
18
1D
b1 B
1#
#946
0!
08
#947
1!
18
b10 B
#948
0!
08
#949
1!
18
b11 B
#950
0!
08
#951
1!
18
b100 B
#952
0!
08
#953
1!
18
b101 B
#954
0!
08
#955
1!
18
b110 B
#956
0!
08
#957
1!
18
b111 B
#958
0!
08
#959
1!
18
b101 F
b1 A
b0 B
#960
0!
08
#961
1!
18
0D
b1 B
0#
#962
0!
08
#963
1!
18
b10 B
#964
0!
08
#965
1!
18
b11 B
#966
0!
08
#967
1!
18
b100 B
#968
0!
08
#969
1!
18
b101 B
#970
0!
08
#971
1!
18
b110 B
#972
0!
08
#973
1!
18
b111 B
#974
0!
08
#975
1!
18
b10 A
b1111001 C
b0 E
b0 B
#976
0!
08
#977
1!
18
1D
b1 B
1#
#978
0!
08
#979
1!
18
b10 B
#980
0!
08
#981
1!
18
b11 B
#982
0!
08
#983
1!
18
b100 B
#984
0!
08
#985
1!
18
b101 B
#986
0!
08
#987
1!
18
b110 B
#988
0!
08
#989
1!
18
b111 B
#990
0!
08
#991
1!
18
b1 E
b0 B
#992
0!
08
#993
1!
18
0D
b1 B
0#
#994
0!
08
#995
1!
18
b10 B
#996
0!
08
#997
1!
18
b11 B
#998
0!
08
#999
1!
18
b100 B
#1000
0!
08
#1001
1!
18
b101 B
#1002
0!
08
#1003
1!
18
b110 B
#1004
0!
08
#1005
1!
18
b111 B
#1006
0!
08
#1007
1!
18
b10 E
b0 B
#1008
0!
08
#1009
1!
18
b1 B
#1010
0!
08
