vsim_uart/uart.v
module uart
#(
    parameter DELAY_FRAMES = 234 // 27,000,000 (27Mhz) / 115200 Baud rate
)
(
    input clk,
    input uart_rx,
    output uart_tx,
    output reg [5:0] led,
    input btn1
);

localparam HALF_DELAY_WAIT = (DELAY_FRAMES / 2);

reg [3:0] rxState = 0;
reg [12:0] rxCounter = 0;
reg [7:0] dataIn = 0;
reg [2:0] rxBitNumber = 0;
reg byteReady = 0;

localparam RX_STATE_IDLE = 0;
localparam RX_STATE_START_BIT = 1;
localparam RX_STATE_READ_WAIT = 2;
localparam RX_STATE_READ = 3;
localparam RX_STATE_STOP_BIT = 5;

always @(posedge clk) begin
    case (rxState)
        RX_STATE_IDLE: begin
            if (uart_rx == 0) begin
                rxState <= RX_STATE_START_BIT;
                rxCounter <= 1;
                rxBitNumber <= 0;
                byteReady <= 0;
            end
        end 
        RX_STATE_START_BIT: begin
            if (rxCounter == HALF_DELAY_WAIT) begin
                rxState <= RX_STATE_READ_WAIT;
                rxCounter <= 1;
            end else 
                rxCounter <= rxCounter + 1;
        end
        RX_STATE_READ_WAIT: begin
            rxCounter <= rxCounter + 1;
            if ((rxCounter + 1) == DELAY_FRAMES) begin
                rxState <= RX_STATE_READ;
            end
        end
        RX_STATE_READ: begin
            rxCounter <= 1;
            dataIn <= {uart_rx, dataIn[7:1]};
            rxBitNumber <= rxBitNumber + 1;
            if (rxBitNumber == 3'b111)
                rxState <= RX_STATE_STOP_BIT;
            else
                rxState <= RX_STATE_READ_WAIT;
        end
        RX_STATE_STOP_BIT: begin
            rxCounter <= rxCounter + 1;
            if ((rxCounter + 1) == DELAY_FRAMES) begin
                rxState <= RX_STATE_IDLE;
                rxCounter <= 0;
                byteReady <= 1;
            end
        end
    endcase
end

always @(posedge clk) begin
    if (byteReady) begin
        led <= ~dataIn[5:0];
    end
end

reg [3:0] txState = 0;
reg [24:0] txCounter = 0;
reg [7:0] dataOut = 0;
reg txPinRegister = 1;
reg [2:0] txBitNumber = 0;
reg [3:0] txByteCounter = 0;

assign uart_tx = txPinRegister;

localparam MEMORY_LENGTH = 12;
reg [7:0] testMemory [MEMORY_LENGTH-1:0];

initial begin
    testMemory[0] = "L";
    testMemory[1] = "u";
    testMemory[2] = "s";
    testMemory[3] = "h";
    testMemory[4] = "a";
    testMemory[5] = "y";
    testMemory[6] = " ";
    testMemory[7] = "L";
    testMemory[8] = "a";
    testMemory[9] = "b";
    testMemory[10] = "s";
    testMemory[11] = " ";
end

localparam TX_STATE_IDLE = 0;
localparam TX_STATE_START_BIT = 1;
localparam TX_STATE_WRITE = 2;
localparam TX_STATE_STOP_BIT = 3;
localparam TX_STATE_DEBOUNCE = 4;

always @(posedge clk) begin
    case (txState)
        TX_STATE_IDLE: begin
            if (btn1 == 0) begin
                txState <= TX_STATE_START_BIT;
                txCounter <= 0;
                txByteCounter <= 0;
            end
            else begin
                txPinRegister <= 1;
            end
        end 
        TX_STATE_START_BIT: begin
            txPinRegister <= 0;
            if ((txCounter + 1) == DELAY_FRAMES) begin
                txState <= TX_STATE_WRITE;
                dataOut <= testMemory[txByteCounter];
                txBitNumber <= 0;
                txCounter <= 0;
            end else 
                txCounter <= txCounter + 1;
        end
        TX_STATE_WRITE: begin
            txPinRegister <= dataOut[txBitNumber];
            if ((txCounter + 1) == DELAY_FRAMES) begin
                if (txBitNumber == 3'b111) begin
                    txState <= TX_STATE_STOP_BIT;
                end else begin
                    txState <= TX_STATE_WRITE;
                    txBitNumber <= txBitNumber + 1;
                end
                txCounter <= 0;
            end else 
                txCounter <= txCounter + 1;
        end
        TX_STATE_STOP_BIT: begin
            txPinRegister <= 1;
            if ((txCounter + 1) == DELAY_FRAMES) begin
                if (txByteCounter == MEMORY_LENGTH - 1) begin
                    txState <= TX_STATE_DEBOUNCE;
                end else begin
                    txByteCounter <= txByteCounter + 1;
                    txState <= TX_STATE_START_BIT;
                end
                txCounter <= 0;
            end else 
                txCounter <= txCounter + 1;
        end
        TX_STATE_DEBOUNCE: begin
            if (txCounter == 23'b111111111111111111) begin
                if (btn1 == 1) 
                    txState <= TX_STATE_IDLE;
            end else
                txCounter <= txCounter + 1;
        end
    endcase      
end
endmodule

vsim_uart/uart_tb.v

module test();
  reg clk = 0;
  reg uart_rx = 1;
  wire uart_tx;
  wire [5:0] led;
  reg btn = 1;

  uart #(8'd8) u(
    clk,
    uart_rx,
    uart_tx,
    led,
    btn
  );

  always
    #1  clk = ~clk;

  initial begin
    $display("Starting UART RX");
    $monitor("LED Value %b", led);
    #10 uart_rx=0;

    #16 uart_rx=1;
    #16 uart_rx=1;
    #16 uart_rx=1;
    #16 uart_rx=1;
    #16 uart_rx=1;
    #16 uart_rx=1;
    #16 uart_rx=1;
    #16 uart_rx=1;

    #16 uart_rx=1;
    // #4 btn=0;
    // #4 btn=1;
    #10000 $stop;
  end

  initial begin
    $dumpfile("uart.vcd");
    $dumpvars(0,test);
  end
endmodule

vsim_uart/uart.vcd
$date
	Fri May 10 16:20:28 2024
$end
$version
	ModelSim Version 2020.1
$end
$timescale
	1ps
$end

$scope module test $end
$var reg 1 ! clk $end
$var reg 1 " uart_rx $end
$var wire 1 # uart_tx $end
$var wire 1 $ led [5] $end
$var wire 1 % led [4] $end
$var wire 1 & led [3] $end
$var wire 1 ' led [2] $end
$var wire 1 ( led [1] $end
$var wire 1 ) led [0] $end
$var reg 1 * btn $end

$scope module u $end
$var parameter 8 + DELAY_FRAMES $end
$var parameter 32 , HALF_DELAY_WAIT $end
$var parameter 32 - RX_STATE_IDLE $end
$var parameter 32 . RX_STATE_START_BIT $end
$var parameter 32 / RX_STATE_READ_WAIT $end
$var parameter 32 0 RX_STATE_READ $end
$var parameter 32 1 RX_STATE_STOP_BIT $end
$var parameter 32 2 MEMORY_LENGTH $end
$var parameter 32 3 TX_STATE_IDLE $end
$var parameter 32 4 TX_STATE_START_BIT $end
$var parameter 32 5 TX_STATE_WRITE $end
$var parameter 32 6 TX_STATE_STOP_BIT $end
$var parameter 32 7 TX_STATE_DEBOUNCE $end
$var wire 1 8 clk $end
$var wire 1 9 uart_rx $end
$var wire 1 # uart_tx $end
$var reg 6 : led [5:0] $end
$var wire 1 ; btn1 $end
$var reg 4 < rxState [3:0] $end
$var reg 13 = rxCounter [12:0] $end
$var reg 8 > dataIn [7:0] $end
$var reg 3 ? rxBitNumber [2:0] $end
$var reg 1 @ byteReady $end
$var reg 4 A txState [3:0] $end
$var reg 25 B txCounter [24:0] $end
$var reg 8 C dataOut [7:0] $end
$var reg 1 D txPinRegister $end
$var reg 3 E txBitNumber [2:0] $end
$var reg 4 F txByteCounter [3:0] $end
$upscope $end
$upscope $end
$enddefinitions $end
#0
$dumpvars
0!
1"
1*
bx :
b0 <
b0 =
b0 >
b0 ?
0@
b0 A
b0 B
b0 C
1D
b0 E
b0 F
b1000 +
b100 ,
b0 -
b1 .
b10 /
b11 0
b101 1
b1100 2
b0 3
b1 4
b10 5
b11 6
b100 7
1#
x)
x(
x'
x&
x%
x$
1;
19
08
$end
#1
1!
18
#2
0!
08
#3
1!
18
#4
0!
08
#5
1!
18
#6
0!
08
#7
1!
18
#8
0!
08
#9
1!
18
#10
0"
0!
09
08
#11
1!
18
b1 <
b1 =
#12
0!
08
#13
1!
18
b10 =
#14
0!
08
#15
1!
18
b11 =
#16
0!
08
#17
1!
18
b100 =
#18
0!
08
#19
1!
18
b10 <
b1 =
#20
0!
08
#21
1!
18
b10 =
#22
0!
08
#23
1!
18
b11 =
#24
0!
08
#25
1!
18
b100 =
#26
1"
0!
19
08
#27
1!
18
b101 =
#28
0!
08
#29
1!
18
b110 =
#30
0!
08
#31
1!
18
b111 =
#32
0!
08
#33
1!
18
b1000 =
b11 <
#34
0!
08
#35
1!
18
b1 =
b10000000 >
b1 ?
b10 <
#36
0!
08
#37
1!
18
b10 =
#38
0!
08
#39
1!
18
b11 =
#40
0!
08
#41
1!
18
b100 =
#42
0!
08
#43
1!
18
b101 =
#44
0!
08
#45
1!
18
b110 =
#46
0!
08
#47
1!
18
b111 =
#48
0!
08
#49
1!
18
b1000 =
b11 <
#50
0!
08
#51
1!
18
b1 =
b11000000 >
b10 ?
b10 <
#52
0!
08
#53
1!
18
b10 =
#54
0!
08
#55
1!
18
b11 =
#56
0!
08
#57
1!
18
b100 =
#58
0!
08
#59
1!
18
b101 =
#60
0!
08
#61
1!
18
b110 =
#62
0!
08
#63
1!
18
b111 =
#64
0!
08
#65
1!
18
b1000 =
b11 <
#66
0!
08
#67
1!
18
b1 =
b11100000 >
b11 ?
b10 <
#68
0!
08
#69
1!
18
b10 =
#70
0!
08
#71
1!
18
b11 =
#72
0!
08
#73
1!
18
b100 =
#74
0!
08
#75
1!
18
b101 =
#76
0!
08
#77
1!
18
b110 =
#78
0!
08
#79
1!
18
b111 =
#80
0!
08
#81
1!
18
b1000 =
b11 <
#82
0!
08
#83
1!
18
b1 =
b11110000 >
b100 ?
b10 <
#84
0!
08
#85
1!
18
b10 =
#86
0!
08
#87
1!
18
b11 =
#88
0!
08
#89
1!
18
b100 =
#90
0!
08
#91
1!
18
b101 =
#92
0!
08
#93
1!
18
b110 =
#94
0!
08
#95
1!
18
b111 =
#96
0!
08
#97
1!
18
b1000 =
b11 <
#98
0!
08
#99
1!
18
b1 =
b11111000 >
b101 ?
b10 <
#100
0!
08
#101
1!
18
b10 =
#102
0!
08
#103
1!
18
b11 =
#104
0!
08
#105
1!
18
b100 =
#106
0!
08
#107
1!
18
b101 =
#108
0!
08
#109
1!
18
b110 =
#110
0!
08
#111
1!
18
b111 =
#112
0!
08
#113
1!
18
b1000 =
b11 <
#114
0!
08
#115
1!
18
b1 =
b11111100 >
b110 ?
b10 <
#116
0!
08
#117
1!
18
b10 =
#118
0!
08
#119
1!
18
b11 =
#120
0!
08
#121
1!
18
b100 =
#122
0!
08
#123
1!
18
b101 =
#124
0!
08
#125
1!
18
b110 =
#126
0!
08
#127
1!
18
b111 =
#128
0!
08
#129
1!
18
b1000 =
b11 <
#130
0!
08
#131
1!
18
b1 =
b11111110 >
b111 ?
b10 <
#132
0!
08
#133
1!
18
b10 =
#134
0!
08
#135
1!
18
b11 =
#136
0!
08
#137
1!
18
b100 =
#138
0!
08
#139
1!
18
b101 =
#140
0!
08
#141
1!
18
b110 =
#142
0!
08
#143
1!
18
b111 =
#144
0!
08
#145
1!
18
b1000 =
b11 <
#146
0!
08
#147
1!
18
b1 =
b11111111 >
b0 ?
b101 <
#148
0!
08
#149
1!
18
b10 =
#150
0!
08
#151
1!
18
b11 =
#152
0!
08
#153
1!
18
b100 =
#154
0!
08
#155
1!
18
b101 =
#156
0!
08
#157
1!
18
b110 =
#158
0!
08
#159
1!
18
b111 =
#160
0!
08
#161
1!
18
b1000 =
b0 <
b0 =
1@
#162
0!
08
#163
1!
18
b0 :
0)
0(
0'
0&
0%
0$
