00_vsim/1_rtl/uart.sv
module uart
#(
    parameter DELAY_FRAMES = 234 // 27,000,000 (27Mhz) / 115200 Baud rate
    
)
(
    input clk,
    input uart_rx,
    input reset_n,
    output uart_tx,
    output reg [6:0] leds,
    input btn1
);

localparam _0 = 7'b011_1111;
localparam _1 = 7'b000_1001;
localparam _2 = 7'b101_1110;
localparam _3 = 7'b101_1011;
localparam _4 = 7'b110_1001;
localparam _5 = 7'b111_0011;
localparam _6 = 7'b111_0111;
localparam _7 = 7'b001_1001;
localparam _8 = 7'b111_1111;
localparam _9 = 7'b111_1011;

localparam HALF_DELAY_WAIT = (DELAY_FRAMES / 2);

enum reg[2:0]{
    RX_STATE_IDLE       = 0,
    RX_STATE_START_BIT  = 1,
    RX_STATE_READ_WAIT  = 2,
    RX_STATE_READ       = 3,
    RX_STATE_STOP_BIT   = 4
} e_rxState;

reg rxState = e_rxState;
// e_rxState = rxState;
reg [12:0] rxCounter = 0;
reg [7:0] dataIn = 0;
reg [2:0] rxBitNumber = 0;
reg byteReady = 0;

// localparam RX_STATE_IDLE = 0;
// localparam RX_STATE_START_BIT = 1;
// localparam RX_STATE_READ_WAIT = 2;
// localparam RX_STATE_READ = 3;
// localparam RX_STATE_STOP_BIT = 4;

always @(posedge clk or negedge reset_n) begin
    if(~reset_n)begin
        
        rxState <= RX_STATE_IDLE;
        rxCounter <= 0;
        rxBitNumber <= 0;
        byteReady <= 0;
    end
    case (rxState)
        RX_STATE_IDLE: begin
            //wait for bit ready when uart_rx==0, start resive data
            if (uart_rx == 0) begin
                rxState <= RX_STATE_START_BIT;
                rxCounter <= 1;
                rxBitNumber <= 0;
                byteReady <= 0;
            end
        end 
        RX_STATE_START_BIT: begin
            if (rxCounter == HALF_DELAY_WAIT) begin
                rxState <= RX_STATE_READ_WAIT;
                rxCounter <= 1;
            end else 
                rxCounter <= rxCounter + 1;
        end
        RX_STATE_READ_WAIT: begin
            rxCounter <= rxCounter + 1;
            if ((rxCounter + 1) == DELAY_FRAMES) begin
                rxState <= RX_STATE_READ;
            end
        end
        RX_STATE_READ: begin
            rxCounter <= 1;
            dataIn <= {uart_rx, dataIn[7:1]};
            rxBitNumber <= rxBitNumber + 1;
            if (rxBitNumber == 3'b111)
                rxState <= RX_STATE_STOP_BIT;
            else
                rxState <= RX_STATE_READ_WAIT;
        end
        RX_STATE_STOP_BIT: begin
            rxCounter <= rxCounter + 1;
            if ((rxCounter + 1) == DELAY_FRAMES) begin
                rxState <= RX_STATE_IDLE;
                rxCounter <= 0;
                byteReady <= 1;
            end
        end
    endcase
end

always @(posedge clk or negedge reset_n) begin
    if (~reset_n)begin
        leds <=0;
    end
    if (byteReady) begin
        //led <= ~dataIn[5:0];
        case (dataIn)
            0       :   leds <= _0;
            1       :   leds <= _1; 
            2       :   leds <= _2;
            3       :   leds <= _3;
            4       :   leds <= _4;
            5       :   leds <= _5;
            6       :   leds <= _6; 
            7       :   leds <= _7;
            8       :   leds <= _8;
            9       :   leds <= _9;
            default :   leds <= _5;
        endcase
    end
end

reg [3:0] txState = 0;
reg [24:0] txCounter = 0;
reg [7:0] dataOut = 0;
reg txPinRegister = 1;
reg [2:0] txBitNumber = 0;
reg [3:0] txByteCounter = 0;

assign uart_tx = txPinRegister;

localparam MEMORY_LENGTH = 12;
reg [7:0] testMemory [MEMORY_LENGTH-1:0];

initial begin
    testMemory[0] = "L";
    testMemory[1] = "u";
    testMemory[2] = "s";
    testMemory[3] = "h";
    testMemory[4] = "a";
    testMemory[5] = "y";
    testMemory[6] = " ";
    testMemory[7] = "L";
    testMemory[8] = "a";
    testMemory[9] = "b";
    testMemory[10] = "s";
    testMemory[11] = " ";
end

localparam TX_STATE_IDLE = 0;
localparam TX_STATE_START_BIT = 1;
localparam TX_STATE_WRITE = 2;
localparam TX_STATE_STOP_BIT = 3;
localparam TX_STATE_DEBOUNCE = 4;

always @(posedge clk) begin
    case (txState)
        TX_STATE_IDLE: begin
            if (btn1 == 0) begin
                txState <= TX_STATE_START_BIT;
                txCounter <= 0;
                txByteCounter <= 0;
            end
            else begin
                txPinRegister <= 1;
            end
        end 
        TX_STATE_START_BIT: begin
            txPinRegister <= 0;
            if ((txCounter + 1) == DELAY_FRAMES) begin
                txState <= TX_STATE_WRITE;
                dataOut <= testMemory[txByteCounter];
                txBitNumber <= 0;
                txCounter <= 0;
            end else 
                txCounter <= txCounter + 1;
        end
        TX_STATE_WRITE: begin
            txPinRegister <= dataOut[txBitNumber];
            if ((txCounter + 1) == DELAY_FRAMES) begin
                if (txBitNumber == 3'b111) begin
                    txState <= TX_STATE_STOP_BIT;
                end else begin
                    txState <= TX_STATE_WRITE;
                    txBitNumber <= txBitNumber + 1;
                end
                txCounter <= 0;
            end else 
                txCounter <= txCounter + 1;
        end
        TX_STATE_STOP_BIT: begin
            txPinRegister <= 1;
            if ((txCounter + 1) == DELAY_FRAMES) begin
                if (txByteCounter == MEMORY_LENGTH - 1) begin
                    txState <= TX_STATE_DEBOUNCE;
                end else begin
                    txByteCounter <= txByteCounter + 1;
                    txState <= TX_STATE_START_BIT;
                end
                txCounter <= 0;
            end else 
                txCounter <= txCounter + 1;
        end
        TX_STATE_DEBOUNCE: begin
            if (txCounter == 23'b111111111111111111) begin
                if (btn1 == 1) 
                    txState <= TX_STATE_IDLE;
            end else
                txCounter <= txCounter + 1;
        end
    endcase      
end
endmodule

00_vsim/2_testbench/testbench.sv
module testbench();
enum reg [1:0]{
    idle    = 0,
    start   = 1,
    data    = 2,
    stop    = 3
}uart_ez_state = idle;

    // ----------- registers -----------
    reg clk       = 0;
    reg uart_rx   = 1;
    reg t_reset_n = 1;
    reg btn       = 1;
    reg t_uart_tx = 1;
    reg [7:0] t_random_value = 0;
    // ----------- wires -----------
    wire       uart_tx;
    wire [5:0] led;
    integer uart_bit;

    // ----------- device under test -----------
    uart #(8'd8) u(
        .clk     /*  input       */ (clk      )
    ,   .uart_rx /*  input       */ (t_uart_tx)
    ,   .reset_n /*  input       */ (t_reset_n)
    ,   .btn1    /*  input       */ (btn      )
    ,   .uart_tx /* output       */ (         )
    ,   .leds    /* output [6:0] */ (         )
    );

    // ----------- system signal generator-----------
    always #1  clk = ~clk;

    // ----------- tasks -----------
    task write_data(input [7:0] wdata);
        uart_ez_state <= start;
        t_uart_tx     <= 0;
        #16;

        for (uart_bit = 7; uart_bit >= 0; uart_bit--) begin
            uart_ez_state <= data;
            t_uart_tx     <= wdata[uart_bit];
            #16;
        end

        uart_ez_state <= stop;
        t_uart_tx     <= 1;
        #16;

        uart_ez_state <= idle;
        uart_bit      <= 7;
    endtask : write_data

    // ----------- test scenarios -----------
    initial begin
    $display("Starting UART RX");
    $monitor("LED Value %b", led);
    #1000;

    // t_random_value = $urandom_range(0,255);
    // write_data(t_random_value);
    // t_random_value = 0;

    write_data(8'hA5);

    // #4 btn=0;
    // #4 btn=1;
    #1000 $stop;
    end

    // ----------- dumping wave -----------
    initial begin
    $dumpfile("uart.vcd");
    $dumpvars(0,testbench);
    end
endmodule

00_vsim/uart.vcd
$date
	Thu May 16 16:30:11 2024
$end
$version
	ModelSim Version 2020.1
$end
$timescale
	1ps
$end

$scope module testbench $end
$var reg 2 ! uart_ez_state [1:0] $end
$var reg 1 " clk $end
$var reg 1 # uart_rx $end
$var reg 1 $ t_reset_n $end
$var reg 1 % btn $end
$var reg 1 & t_uart_tx $end
$var reg 8 ' t_random_value [7:0] $end
$var wire 1 ( uart_tx $end
$var wire 1 ) led [5] $end
$var wire 1 * led [4] $end
$var wire 1 + led [3] $end
$var wire 1 , led [2] $end
$var wire 1 - led [1] $end
$var wire 1 . led [0] $end
$var integer 32 / uart_bit $end

$scope task write_data $end
$var reg 8 0 wdata [7:0] $end
$upscope $end

$scope module u $end
$var parameter 8 1 DELAY_FRAMES $end
$var parameter 7 2 _0 $end
$var parameter 7 3 _1 $end
$var parameter 7 4 _2 $end
$var parameter 7 5 _3 $end
$var parameter 7 6 _4 $end
$var parameter 7 7 _5 $end
$var parameter 7 8 _6 $end
$var parameter 7 9 _7 $end
$var parameter 7 : _8 $end
$var parameter 7 ; _9 $end
$var parameter 32 < HALF_DELAY_WAIT $end
$var parameter 32 = MEMORY_LENGTH $end
$var parameter 32 > TX_STATE_IDLE $end
$var parameter 32 ? TX_STATE_START_BIT $end
$var parameter 32 @ TX_STATE_WRITE $end
$var parameter 32 A TX_STATE_STOP_BIT $end
$var parameter 32 B TX_STATE_DEBOUNCE $end
$var wire 1 C clk $end
$var wire 1 D uart_rx $end
$var wire 1 E reset_n $end
$var wire 1 F uart_tx $end
$var reg 7 G leds [6:0] $end
$var wire 1 H btn1 $end
$var reg 3 I e_rxState [2:0] $end
$var reg 1 J rxState $end
$var reg 13 K rxCounter [12:0] $end
$var reg 8 L dataIn [7:0] $end
$var reg 3 M rxBitNumber [2:0] $end
$var reg 1 N byteReady $end
$var reg 4 O txState [3:0] $end
$var reg 25 P txCounter [24:0] $end
$var reg 8 Q dataOut [7:0] $end
$var reg 1 R txPinRegister $end
$var reg 3 S txBitNumber [2:0] $end
$var reg 4 T txByteCounter [3:0] $end
$upscope $end
$upscope $end
$enddefinitions $end
#0
$dumpvars
b0 !
0"
1#
1$
1%
1&
b0 '
bx G
bx I
xJ
b0 K
b0 L
b0 M
0N
b0 O
b0 P
b0 Q
1R
b0 S
b0 T
bx 0
b1000 1
b111111 2
b1001 3
b1011110 4
b1011011 5
b1101001 6
b1110011 7
b1110111 8
b11001 9
b1111111 :
b1111011 ;
b100 <
b1100 =
b0 >
b1 ?
b10 @
b11 A
b100 B
bx /
z(
z.
z-
z,
z+
z*
z)
0C
1D
1E
1H
1F
$end
#1
1"
1C
#2
0"
0C
#3
1"
1C
#4
0"
0C
#5
1"
1C
#6
0"
0C
#7
1"
1C
#8
0"
0C
#9
1"
1C
#10
0"
0C
#11
1"
1C
#12
0"
0C
#13
1"
1C
#14
0"
0C
#15
1"
1C
#16
0"
0C
#17
1"
1C
#18
0"
0C
#19
1"
1C
#20
0"
0C
#21
1"
1C
#22
0"
0C
#23
1"
1C
#24
0"
0C
#25
1"
1C
#26
0"
0C
#27
1"
1C
#28
0"
0C
#29
1"
1C
#30
0"
0C
#31
1"
1C
#32
0"
0C
#33
1"
1C
#34
0"
0C
#35
1"
1C
#36
0"
0C
#37
1"
1C
#38
0"
0C
#39
1"
1C
#40
0"
0C
#41
1"
1C
#42
0"
0C
#43
1"
1C
#44
0"
0C
#45
1"
1C
#46
0"
0C
#47
1"
1C
#48
0"
0C
#49
1"
1C
#50
0"
0C
#51
1"
1C
#52
0"
0C
#53
1"
1C
#54
0"
0C
#55
1"
1C
#56
0"
0C
#57
1"
1C
#58
0"
0C
#59
1"
1C
#60
0"
0C
#61
1"
1C
#62
0"
0C
#63
1"
1C
#64
0"
0C
#65
1"
1C
#66
0"
0C
#67
1"
1C
#68
0"
0C
#69
1"
1C
#70
0"
0C
#71
1"
1C
#72
0"
0C
#73
1"
1C
#74
0"
0C
#75
1"
1C
#76
0"
0C
#77
1"
1C
#78
0"
0C
#79
1"
1C
#80
0"
0C
#81
1"
1C
#82
0"
0C
#83
1"
1C
#84
0"
0C
#85
1"
1C
#86
0"
0C
#87
1"
1C
#88
0"
0C
#89
1"
1C
#90
0"
0C
#91
1"
1C
#92
0"
0C
#93
1"
1C
#94
0"
0C
#95
1"
1C
#96
0"
0C
#97
1"
1C
#98
0"
0C
#99
1"
1C
#100
0"
0C
#101
1"
1C
#102
0"
0C
#103
1"
1C
#104
0"
0C
#105
1"
1C
#106
0"
0C
#107
1"
1C
#108
0"
0C
#109
1"
1C
#110
0"
0C
#111
1"
1C
#112
0"
0C
#113
1"
1C
#114
0"
0C
#115
1"
1C
#116
0"
0C
#117
1"
1C
#118
0"
0C
#119
1"
1C
#120
0"
0C
#121
1"
1C
#122
0"
0C
#123
1"
1C
#124
0"
0C
#125
1"
1C
#126
0"
0C
#127
1"
1C
#128
0"
0C
#129
1"
1C
#130
0"
0C
#131
1"
1C
#132
0"
0C
#133
1"
1C
#134
0"
0C
#135
1"
1C
#136
0"
0C
#137
1"
1C
#138
0"
0C
#139
1"
1C
#140
0"
0C
#141
1"
1C
#142
0"
0C
#143
1"
1C
#144
0"
0C
#145
1"
1C
#146
0"
0C
#147
1"
1C
#148
0"
0C
#149
1"
1C
#150
0"
0C
#151
1"
1C
#152
0"
0C
#153
1"
1C
#154
0"
0C
#155
1"
1C
#156
0"
0C
#157
1"
1C
#158
0"
0C
#159
1"
1C
#160
0"
0C
#161
1"
1C
#162
0"
0C
#163
1"
1C
#164
0"
0C
#165
1"
1C
#166
0"
0C
#167
1"
1C
#168
0"
0C
#169
1"
1C
#170
0"
0C
#171
1"
1C
#172
0"
0C
#173
1"
1C
#174
0"
0C
#175
1"
1C
#176
0"
0C
#177
1"
1C
#178
0"
0C
#179
1"
1C
#180
0"
0C
#181
1"
1C
#182
0"
0C
#183
1"
1C
#184
0"
0C
#185
1"
1C
#186
0"
0C
#187
1"
1C
#188
0"
0C
#189
1"
1C
#190
0"
0C
#191
1"
1C
#192
0"
0C
#193
1"
1C
#194
0"
0C
#195
1"
1C
#196
0"
0C
#197
1"
1C
#198
0"
0C
#199
1"
1C
#200
0"
0C
#201
1"
1C
#202
0"
0C
#203
1"
1C
#204
0"
0C
#205
1"
1C
#206
0"
0C
#207
1"
1C
#208
0"
0C
#209
1"
1C
#210
0"
0C
#211
1"
1C
#212
0"
0C
#213
1"
1C
#214
0"
0C
#215
1"
1C
#216
0"
0C
#217
1"
1C
#218
0"
0C
#219
1"
1C
#220
0"
0C
#221
1"
1C
#222
0"
0C
#223
1"
1C
#224
0"
0C
#225
1"
1C
#226
0"
0C
#227
1"
1C
#228
0"
0C
#229
1"
1C
#230
0"
0C
#231
1"
1C
#232
0"
0C
#233
1"
1C
#234
0"
0C
#235
1"
1C
#236
0"
0C
#237
1"
1C
#238
0"
0C
#239
1"
1C
#240
0"
0C
#241
1"
1C
#242
0"
0C
#243
1"
1C
#244
0"
0C
#245
1"
1C
#246
0"
0C
#247
1"
1C
#248
0"
0C
#249
1"
1C
#250
0"
0C
#251
1"
1C
#252
0"
0C
#253
1"
1C
#254
0"
0C
#255
1"
1C
#256
0"
0C
#257
1"
1C
#258
0"
0C
#259
1"
1C
#260
0"
0C
#261
1"
1C
#262
0"
0C
#263
1"
1C
#264
0"
0C
#265
1"
1C
#266
0"
0C
#267
1"
1C
#268
0"
0C
#269
1"
1C
#270
0"
0C
#271
1"
1C
#272
0"
0C
#273
1"
1C
#274
0"
0C
#275
1"
1C
#276
0"
0C
#277
1"
1C
#278
0"
0C
#279
1"
1C
#280
0"
0C
#281
1"
1C
#282
0"
0C
#283
1"
1C
#284
0"
0C
#285
1"
1C
#286
0"
0C
#287
1"
1C
#288
0"
0C
#289
1"
1C
#290
0"
0C
#291
1"
1C
#292
0"
0C
#293
1"
1C
#294
0"
0C
#295
1"
1C
#296
0"
0C
#297
1"
1C
#298
0"
0C
#299
1"
1C
#300
0"
0C
#301
1"
1C
#302
0"
0C
#303
1"
1C
#304
0"
0C
#305
1"
1C
#306
0"
0C
#307
1"
1C
#308
0"
0C
#309
1"
1C
#310
0"
0C
#311
1"
1C
#312
0"
0C
#313
1"
1C
#314
0"
0C
#315
1"
1C
#316
0"
0C
#317
1"
1C
#318
0"
0C
#319
1"
1C
#320
0"
0C
#321
1"
1C
#322
0"
0C
#323
1"
1C
#324
0"
0C
#325
1"
1C
#326
0"
0C
#327
1"
1C
#328
0"
0C
#329
1"
1C
#330
0"
0C
#331
1"
1C
#332
0"
0C
#333
1"
1C
#334
0"
0C
#335
1"
1C
#336
0"
0C
#337
1"
1C
#338
0"
0C
#339
1"
1C
#340
0"
0C
#341
1"
1C
#342
0"
0C
#343
1"
1C
#344
0"
0C
#345
1"
1C
#346
0"
0C
#347
1"
1C
#348
0"
0C
#349
1"
1C
#350
0"
0C
#351
1"
1C
#352
0"
0C
#353
1"
1C
#354
0"
0C
#355
1"
1C
#356
0"
0C
#357
1"
1C
#358
0"
0C
#359
1"
1C
#360
0"
0C
#361
1"
1C
#362
0"
0C
#363
1"
1C
#364
0"
0C
#365
1"
1C
#366
0"
0C
#367
1"
1C
#368
0"
0C
#369
1"
1C
#370
0"
0C
#371
1"
1C
#372
0"
0C
#373
1"
1C
#374
0"
0C
#375
1"
1C
#376
0"
0C
#377
1"
1C
#378
0"
0C
#379
1"
1C
#380
0"
0C
#381
1"
1C
#382
0"
0C
#383
1"
1C
#384
0"
0C
#385
1"
1C
#386
0"
0C
#387
1"
1C
#388
0"
0C
#389
1"
1C
#390
0"
0C
#391
1"
1C
#392
0"
0C
#393
1"
1C
#394
0"
0C
#395
1"
1C
#396
0"
0C
#397
1"
1C
#398
0"
0C
#399
1"
1C
#400
0"
0C
#401
1"
1C
#402
0"
0C
#403
1"
1C
#404
0"
0C
#405
1"
1C
#406
0"
0C
#407
1"
1C
#408
0"
0C
#409
1"
1C
#410
0"
0C
#411
1"
1C
#412
0"
0C
#413
1"
1C
#414
0"
0C
#415
1"
1C
#416
0"
0C
#417
1"
1C
#418
0"
0C
#419
1"
1C
#420
0"
0C
#421
1"
1C
#422
0"
0C
#423
1"
1C
#424
0"
0C
#425
1"
1C
#426
0"
0C
#427
1"
1C
#428
0"
0C
#429
1"
1C
#430
0"
0C
#431
1"
1C
#432
0"
0C
#433
1"
1C
#434
0"
0C
#435
1"
1C
#436
0"
0C
#437
1"
1C
#438
0"
0C
#439
1"
1C
#440
0"
0C
#441
1"
1C
#442
0"
0C
#443
1"
1C
#444
0"
0C
#445
1"
1C
#446
0"
0C
#447
1"
1C
#448
0"
0C
#449
1"
1C
#450
0"
0C
#451
1"
1C
#452
0"
0C
#453
1"
1C
#454
0"
0C
#455
1"
1C
#456
0"
0C
#457
1"
1C
#458
0"
0C
#459
1"
1C
#460
0"
0C
#461
1"
1C
#462
0"
0C
#463
1"
1C
#464
0"
0C
#465
1"
1C
#466
0"
0C
#467
1"
1C
#468
0"
0C
#469
1"
1C
#470
0"
0C
#471
1"
1C
#472
0"
0C
#473
1"
1C
#474
0"
0C
#475
1"
1C
#476
0"
0C
#477
1"
1C
#478
0"
0C
#479
1"
1C
#480
0"
0C
#481
1"
1C
#482
0"
0C
#483
1"
1C
#484
0"
0C
#485
1"
1C
#486
0"
0C
#487
1"
1C
#488
0"
0C
#489
1"
1C
#490
0"
0C
#491
1"
1C
#492
0"
0C
#493
1"
1C
#494
0"
0C
#495
1"
1C
#496
0"
0C
#497
1"
1C
#498
0"
0C
#499
1"
1C
#500
0"
0C
#501
1"
1C
#502
0"
0C
#503
1"
1C
#504
0"
0C
#505
1"
1C
#506
0"
0C
#507
1"
1C
#508
0"
0C
#509
1"
1C
#510
0"
0C
#511
1"
1C
#512
0"
0C
#513
1"
1C
#514
0"
0C
#515
1"
1C
#516
0"
0C
#517
1"
1C
#518
0"
0C
#519
1"
1C
#520
0"
0C
#521
1"
1C
#522
0"
0C
#523
1"
1C
#524
0"
0C
#525
1"
1C
#526
0"
0C
#527
1"
1C
#528
0"
0C
#529
1"
1C
#530
0"
0C
#531
1"
1C
#532
0"
0C
#533
1"
1C
#534
0"
0C
#535
1"
1C
#536
0"
0C
#537
1"
1C
#538
0"
0C
#539
1"
1C
#540
0"
0C
#541
1"
1C
#542
0"
0C
#543
1"
1C
#544
0"
0C
#545
1"
1C
#546
0"
0C
#547
1"
1C
#548
0"
0C
#549
1"
1C
#550
0"
0C
#551
1"
1C
#552
0"
0C
#553
1"
1C
#554
0"
0C
#555
1"
1C
#556
0"
0C
#557
1"
1C
#558
0"
0C
#559
1"
1C
#560
0"
0C
#561
1"
1C
#562
0"
0C
#563
1"
1C
#564
0"
0C
#565
1"
1C
#566
0"
0C
#567
1"
1C
#568
0"
0C
#569
1"
1C
#570
0"
0C
#571
1"
1C
#572
0"
0C
#573
1"
1C
#574
0"
0C
#575
1"
1C
#576
0"
0C
#577
1"
1C
#578
0"
0C
#579
1"
1C
#580
0"
0C
#581
1"
1C
#582
0"
0C
#583
1"
1C
#584
0"
0C
#585
1"
1C
#586
0"
0C
#587
1"
1C
#588
0"
0C
#589
1"
1C
#590
0"
0C
#591
1"
1C
#592
0"
0C
#593
1"
1C
#594
0"
0C
#595
1"
1C
#596
0"
0C
#597
1"
1C
#598
0"
0C
#599
1"
1C
#600
0"
0C
#601
1"
1C
#602
0"
0C
#603
1"
1C
#604
0"
0C
#605
1"
1C
#606
0"
0C
#607
1"
1C
#608
0"
0C
#609
1"
1C
#610
0"
0C
#611
1"
1C
#612
0"
0C
#613
1"
1C
#614
0"
0C
#615
1"
1C
#616
0"
0C
#617
1"
1C
#618
0"
0C
#619
1"
1C
#620
0"
0C
#621
1"
1C
#622
0"
0C
#623
1"
1C
#624
0"
0C
#625
1"
1C
#626
0"
0C
#627
1"
1C
#628
0"
0C
#629
1"
1C
#630
0"
0C
#631
1"
1C
#632
0"
0C
#633
1"
1C
#634
0"
0C
#635
1"
1C
#636
0"
0C
#637
1"
1C
#638
0"
0C
#639
1"
1C
#640
0"
0C
#641
1"
1C
#642
0"
0C
#643
1"
1C
#644
0"
0C
#645
1"
1C
#646
0"
0C
#647
1"
1C
#648
0"
0C
#649
1"
1C
#650
0"
0C
#651
1"
1C
#652
0"
0C
#653
1"
1C
#654
0"
0C
#655
1"
1C
#656
0"
0C
#657
1"
1C
#658
0"
0C
#659
1"
1C
#660
0"
0C
#661
1"
1C
#662
0"
0C
#663
1"
1C
#664
0"
0C
#665
1"
1C
#666
0"
0C
#667
1"
1C
#668
0"
0C
#669
1"
1C
#670
0"
0C
#671
1"
1C
#672
0"
0C
#673
1"
1C
#674
0"
0C
#675
1"
1C
#676
0"
0C
#677
1"
1C
#678
0"
0C
#679
1"
1C
#680
0"
0C
#681
1"
1C
#682
0"
0C
#683
1"
1C
#684
0"
0C
#685
1"
1C
#686
0"
0C
#687
1"
1C
#688
0"
0C
#689
1"
1C
#690
0"
0C
#691
1"
1C
#692
0"
0C
#693
1"
1C
#694
0"
0C
#695
1"
1C
#696
0"
0C
#697
1"
1C
#698
0"
0C
#699
1"
1C
#700
0"
0C
#701
1"
1C
#702
0"
0C
#703
1"
1C
#704
0"
0C
#705
1"
1C
#706
0"
0C
#707
1"
1C
#708
0"
0C
#709
1"
1C
#710
0"
0C
#711
1"
1C
#712
0"
0C
#713
1"
1C
#714
0"
0C
#715
1"
1C
#716
0"
0C
#717
1"
1C
#718
0"
0C
#719
1"
1C
#720
0"
0C
#721
1"
1C
#722
0"
0C
#723
1"
1C
#724
0"
0C
#725
1"
1C
#726
0"
0C
#727
1"
1C
#728
0"
0C
#729
1"
1C
#730
0"
0C
#731
1"
1C
#732
0"
0C
#733
1"
1C
#734
0"
0C
#735
1"
1C
#736
0"
0C
#737
1"
1C
#738
0"
0C
#739
1"
1C
#740
0"
0C
#741
1"
1C
#742
0"
0C
#743
1"
1C
#744
0"
0C
#745
1"
1C
#746
0"
0C
#747
1"
1C
#748
0"
0C
#749
1"
1C
#750
0"
0C
#751
1"
1C
#752
0"
0C
#753
1"
1C
#754
0"
0C
#755
1"
1C
#756
0"
0C
#757
1"
1C
#758
0"
0C
#759
1"
1C
#760
0"
0C
#761
1"
1C
#762
0"
0C
#763
1"
1C
#764
0"
0C
#765
1"
1C
#766
0"
0C
#767
1"
1C
#768
0"
0C
#769
1"
1C
#770
0"
0C
#771
1"
1C
#772
0"
0C
#773
1"
1C
#774
0"
0C
#775
1"
1C
#776
0"
0C
#777
1"
1C
#778
0"
0C
#779
1"
1C
#780
0"
0C
#781
1"
1C
#782
0"
0C
#783
1"
1C
#784
0"
0C
#785
1"
1C
#786
0"
0C
#787
1"
1C
#788
0"
0C
#789
1"
1C
#790
0"
0C
#791
1"
1C
#792
0"
0C
#793
1"
1C
#794
0"
0C
#795
1"
1C
#796
0"
0C
#797
1"
1C
#798
0"
0C
#799
1"
1C
#800
0"
0C
#801
1"
1C
#802
0"
0C
#803
1"
1C
#804
0"
0C
#805
1"
1C
#806
0"
0C
#807
1"
1C
#808
0"
0C
#809
1"
1C
#810
0"
0C
#811
1"
1C
#812
0"
0C
#813
1"
1C
#814
0"
0C
#815
1"
1C
#816
0"
0C
#817
1"
1C
#818
0"
0C
#819
1"
1C
#820
0"
0C
#821
1"
1C
#822
0"
0C
#823
1"
1C
#824
0"
0C
#825
1"
1C
#826
0"
0C
#827
1"
1C
#828
0"
0C
#829
1"
1C
#830
0"
0C
#831
1"
1C
#832
0"
0C
#833
1"
1C
#834
0"
0C
#835
1"
1C
#836
0"
0C
#837
1"
1C
#838
0"
0C
#839
1"
1C
#840
0"
0C
#841
1"
1C
#842
0"
0C
#843
1"
1C
#844
0"
0C
#845
1"
1C
#846
0"
0C
#847
1"
1C
#848
0"
0C
#849
1"
1C
#850
0"
0C
#851
1"
1C
#852
0"
0C
#853
1"
1C
#854
0"
0C
#855
1"
1C
#856
0"
0C
#857
1"
1C
#858
0"
0C
#859
1"
1C
#860
0"
0C
#861
1"
1C
#862
0"
0C
#863
1"
1C
#864
0"
0C
#865
1"
1C
#866
0"
0C
#867
1"
1C
#868
0"
0C
#869
1"
1C
#870
0"
0C
#871
1"
1C
#872
0"
0C
#873
1"
1C
#874
0"
0C
#875
1"
1C
#876
0"
0C
#877
1"
1C
#878
0"
0C
#879
1"
1C
#880
0"
0C
#881
1"
1C
#882
0"
0C
#883
1"
1C
#884
0"
0C
#885
1"
1C
#886
0"
0C
#887
1"
1C
#888
0"
0C
#889
1"
1C
#890
0"
0C
#891
1"
1C
#892
0"
0C
#893
1"
1C
#894
0"
0C
#895
1"
1C
#896
0"
0C
#897
1"
1C
#898
0"
0C
#899
1"
1C
#900
0"
0C
#901
1"
1C
#902
0"
0C
#903
1"
1C
#904
0"
0C
#905
1"
1C
#906
0"
0C
#907
1"
1C
#908
0"
0C
#909
1"
1C
#910
0"
0C
#911
1"
1C
#912
0"
0C
#913
1"
1C
#914
0"
0C
#915
1"
1C
#916
0"
0C
#917
1"
1C
#918
0"
0C
#919
1"
1C
#920
0"
0C
#921
1"
1C
#922
0"
0C
#923
1"
1C
#924
0"
0C
#925
1"
1C
#926
0"
0C
#927
1"
1C
#928
0"
0C
#929
1"
1C
#930
0"
0C
#931
1"
1C
#932
0"
0C
#933
1"
1C
#934
0"
0C
#935
1"
1C
#936
0"
0C
#937
1"
1C
#938
0"
0C
#939
1"
1C
#940
0"
0C
#941
1"
1C
#942
0"
0C
#943
1"
1C
#944
0"
0C
#945
1"
1C
#946
0"
0C
#947
1"
1C
#948
0"
0C
#949
1"
1C
#950
0"
0C
#951
1"
1C
#952
0"
0C
#953
1"
1C
#954
0"
0C
#955
1"
1C
#956
0"
0C
#957
1"
1C
#958
0"
0C
#959
1"
1C
#960
0"
0C
#961
1"
1C
#962
0"
0C
#963
1"
1C
#964
0"
0C
#965
1"
1C
#966
0"
0C
#967
1"
1C
#968
0"
0C
#969
1"
1C
#970
0"
0C
#971
1"
1C
#972
0"
0C
#973
1"
1C
#974
0"
0C
#975
1"
1C
#976
0"
0C
#977
1"
1C
#978
0"
0C
#979
1"
1C
#980
0"
0C
#981
1"
1C
#982
0"
0C
#983
1"
1C
#984
0"
0C
#985
1"
1C
#986
0"
0C
#987
1"
1C
#988
0"
0C
#989
1"
1C
#990
0"
0C
#991
1"
1C
#992
0"
0C
#993
1"
1C
#994
0"
0C
#995
1"
1C
#996
0"
0C
#997
1"
1C
#998
0"
0C
#999
1"
1C
#1000
b10100101 0
0"
0C
b1 !
0&
0D
#1001
1"
1C
#1002
0"
0C
#1003
1"
1C
#1004
0"
0C
#1005
1"
1C
#1006
0"
0C
#1007
1"
1C
#1008
0"
0C
#1009
1"
1C
#1010
0"
0C
#1011
1"
1C
#1012
0"
0C
#1013
1"
1C
#1014
0"
0C
#1015
1"
1C
#1016
b111 /
0"
0C
b10 !
1&
1D
#1017
1"
1C
#1018
0"
0C
#1019
1"
1C
#1020
0"
0C
#1021
1"
1C
#1022
0"
0C
#1023
1"
1C
#1024
0"
0C
#1025
1"
1C
#1026
0"
0C
#1027
1"
1C
#1028
0"
0C
#1029
1"
1C
#1030
0"
0C
#1031
1"
1C
#1032
b110 /
0"
0C
0&
0D
#1033
1"
1C
#1034
0"
0C
#1035
1"
1C
#1036
0"
0C
#1037
1"
1C
#1038
0"
0C
#1039
1"
1C
#1040
0"
0C
#1041
1"
1C
#1042
0"
0C
#1043
1"
1C
#1044
0"
0C
#1045
1"
1C
#1046
0"
0C
#1047
1"
1C
#1048
b101 /
0"
0C
1&
1D
#1049
1"
1C
#1050
0"
0C
#1051
1"
1C
#1052
0"
0C
#1053
1"
1C
#1054
0"
0C
#1055
1"
1C
#1056
0"
0C
#1057
1"
1C
#1058
0"
0C
#1059
1"
1C
#1060
0"
0C
#1061
1"
1C
#1062
0"
0C
#1063
1"
1C
#1064
b100 /
0"
0C
0&
0D
#1065
1"
1C
#1066
0"
0C
#1067
1"
1C
#1068
0"
0C
#1069
1"
1C
#1070
0"
0C
#1071
1"
1C
#1072
0"
0C
#1073
1"
1C
#1074
0"
0C
#1075
1"
1C
#1076
0"
0C
#1077
1"
1C
#1078
0"
0C
#1079
1"
1C
#1080
b11 /
0"
0C
#1081
1"
1C
#1082
0"
0C
#1083
1"
1C
#1084
0"
0C
#1085
1"
1C
#1086
0"
0C
#1087
1"
1C
#1088
0"
0C
#1089
1"
1C
#1090
0"
0C
#1091
1"
1C
#1092
0"
0C
#1093
1"
1C
#1094
0"
0C
#1095
1"
1C
#1096
b10 /
0"
0C
1&
1D
#1097
1"
1C
#1098
0"
0C
#1099
1"
1C
#1100
0"
0C
#1101
1"
1C
#1102
0"
0C
#1103
1"
1C
